fast_deploy/__init__.py
fast_deploy/api/__init__.py
fast_deploy/api/main.py
fast_deploy/cli.py
fast_deploy/loaders/__init__.py
fast_deploy/loaders/sklearn_loader.py
fast_deploy/model_loader.py
l6n_fast_deploy-0.1.0.dist-info/LICENSE
l6n_fast_deploy-0.1.0.dist-info/METADATA
l6n_fast_deploy-0.1.0.dist-info/WHEEL
l6n_fast_deploy-0.1.0.dist-info/entry_points.txt
l6n_fast_deploy-0.1.0.dist-info/RECORD
