Metadata-Version: 2.1
Name: l6n-fast-deploy
Version: 0.1.0
Summary: FastDeploy é uma ferramenta CLI que simplifica o deploy de modelos de machine learning como APIs REST em containers Docker.
License: Beerware
Author: laranapoli
Author-email: laranapoli0@gmail.com
Requires-Python: >=3.12,<4.0
Classifier: Development Status :: 4 - Beta
Classifier: Environment :: Console
Classifier: License :: Other/Proprietary License
Classifier: Natural Language :: Portuguese (Brazilian)
Classifier: Programming Language :: Python :: 3
Classifier: Programming Language :: Python :: 3.12
Classifier: Programming Language :: Python :: 3.13
Classifier: Topic :: Education
Requires-Dist: fastapi (>=0.115.3,<0.116.0)
Requires-Dist: python-multipart (>=0.0.12,<0.0.13)
Requires-Dist: rich (>=13.9.3,<14.0.0)
Requires-Dist: scikit-learn (>=1.5.2,<2.0.0)
Requires-Dist: typer (>=0.12.5,<0.13.0)
Requires-Dist: uvicorn (>=0.32.0,<0.33.0)
Project-URL: Bug Tracker, https://github.com/laranapoli/fast-deploy/issues
Project-URL: Código, https://github.com/laranapoli/fast-deploy
Project-URL: Documentação, https://fast-deploy.readthedocs.io/pt-br/latest/
